crtools/__init__.py
crtools/_version.py
crtools/api_wrapper.py
crtools/config.py
crtools/crtools.py
crtools/discord.py
crtools/fankit.py
crtools/gdoc.py
crtools/history.py
crtools/io.py
crtools/leagueinfo.py
crtools/memberfactory.py
crtools/scorecalc.py
crtools/locale/crtools.pot
crtools/locale/cn/LC_MESSAGES/crtools.mo
crtools/locale/cn/LC_MESSAGES/crtools.po
crtools/locale/de/LC_MESSAGES/crtools.mo
crtools/locale/de/LC_MESSAGES/crtools.po
crtools/locale/fr/LC_MESSAGES/crtools.mo
crtools/locale/fr/LC_MESSAGES/crtools.po
crtools/locale/it/LC_MESSAGES/crtools.mo
crtools/locale/it/LC_MESSAGES/crtools.po
crtools/locale/pt/LC_MESSAGES/crtools.mo
crtools/locale/pt/LC_MESSAGES/crtools.po
crtools/locale/ru/LC_MESSAGES/crtools.mo
crtools/locale/ru/LC_MESSAGES/crtools.po
crtools/models/__init__.py
crtools/models/clan.py
crtools/models/demerit.py
crtools/models/formermember.py
crtools/models/membercustomrecord.py
crtools/models/memberevent.py
crtools/models/processedmember.py
crtools/models/vacation.py
crtools/models/war.py
crtools/models/warparticipation.py
crtools/models/__pycache__/__init__.cpython-37.pyc
crtools/models/__pycache__/clan.cpython-37.pyc
crtools/models/__pycache__/demerit.cpython-37.pyc
crtools/models/__pycache__/formermember.cpython-37.pyc
crtools/models/__pycache__/membercustomrecord.cpython-37.pyc
crtools/models/__pycache__/memberevent.cpython-37.pyc
crtools/models/__pycache__/processedmember.cpython-37.pyc
crtools/models/__pycache__/vacation.cpython-37.pyc
crtools/models/__pycache__/war.cpython-37.pyc
crtools/models/__pycache__/warparticipation.cpython-37.pyc
crtools/static/crtools.css
crtools/static/crtools.js
crtools/static/dialog.css
crtools/static/fankit.css
crtools/static/filters.css
crtools/static/hero.css
crtools/static/os-assets.css
crtools/static/tablesort-with-number.min.js
crtools/static/images/angry.png
crtools/static/images/arena-league-challenger-1.svg
crtools/static/images/arena-league-challenger-2.svg
crtools-2.16.2.dist-info/LICENSE
crtools-2.16.2.dist-info/METADATA
crtools-2.16.2.dist-info/WHEEL
crtools-2.16.2.dist-info/entry_points.txt
crtools-2.16.2.dist-info/top_level.txt
crtools-2.16.2.dist-info/RECORD
