Metadata-Version: 2.1
Name: crtools
Version: 2.16.2
Summary: Python tools for creating a clan management dashboard for Clash Royale
Home-page: https://github.com/AaronTraas/Clash-Royale-Clan-Tools
Author: Aaron Traas
Author-email: aaron@traas.org
License: LGPLv3+
Project-URL: Bug Reports, https://github.com/AaronTraas/Clash-Royale-Clan-Tools/issues
Project-URL: Source, https://github.com/AaronTraas/Clash-Royale-Clan-Tools
Keywords: ClashRoyale
Platform: UNKNOWN
Classifier: Development Status :: 5 - Production/Stable
Classifier: Intended Audience :: Other Audience
Classifier: License :: OSI Approved :: GNU Lesser General Public License v3 or later (LGPLv3+)
Classifier: Programming Language :: Python :: 3
Requires-Dist: configparser
Requires-Dist: discord-webhook
Requires-Dist: google-api-python-client
Requires-Dist: jinja2
Requires-Dist: pyroyale (>=1.0.3)
Requires-Dist: requests
